agentos/__init__.py
agentos/client.py
agentos/config.py
agentos/main.py
agentos/commands/__init__.py
agentos/commands/agents.py
agentos/commands/api_keys.py
agentos/commands/deploy.py
agentos/commands/login.py
agentos/commands/register.py
agentos/commands/secrets.py
agentos/commands/workers.py
agentos/utils/__init__.py
agentos/utils/config_manager.py
agentos/utils/heartbeat.py
agentos/utils/oauth_server.py
ag2_agentos-0.0.0a18.dist-info/METADATA
ag2_agentos-0.0.0a18.dist-info/WHEEL
ag2_agentos-0.0.0a18.dist-info/entry_points.txt
ag2_agentos-0.0.0a18.dist-info/RECORD
